AndroidJavaJishuBiji/README.md
AndroidJavaJishuBiji/__init__.py
AndroidJavaJishuBiji/__main__.py
AndroidJavaJishuBiji/file.epub
AndroidJavaJishuBiji/index.html
AndroidJavaJishuBiji/css/__init__.py
AndroidJavaJishuBiji/css/annotations.css
AndroidJavaJishuBiji/css/main.css
AndroidJavaJishuBiji/css/normalize.css
AndroidJavaJishuBiji/css/popup.css
AndroidJavaJishuBiji/font/__init__.py
AndroidJavaJishuBiji/font/fontello.eot
AndroidJavaJishuBiji/font/fontello.svg
AndroidJavaJishuBiji/font/fontello.ttf
AndroidJavaJishuBiji/font/fontello.woff
AndroidJavaJishuBiji/img/__init__.py
AndroidJavaJishuBiji/img/annotator-glyph-sprite.png
AndroidJavaJishuBiji/img/annotator-icon-sprite.png
AndroidJavaJishuBiji/img/apple-touch-icon.png
AndroidJavaJishuBiji/img/cancelfullscreen.png
AndroidJavaJishuBiji/img/close.png
AndroidJavaJishuBiji/img/fullscreen.png
AndroidJavaJishuBiji/img/loader.gif
AndroidJavaJishuBiji/img/menu-icon.png
AndroidJavaJishuBiji/img/save.png
AndroidJavaJishuBiji/img/saved.png
AndroidJavaJishuBiji/img/settings-s.png
AndroidJavaJishuBiji/img/settings.png
AndroidJavaJishuBiji/img/star.png
AndroidJavaJishuBiji/js/__init__.py
AndroidJavaJishuBiji/js/epub.js
AndroidJavaJishuBiji/js/epub.min.js
AndroidJavaJishuBiji/js/epub.min.map
AndroidJavaJishuBiji/js/hooks.min.js
AndroidJavaJishuBiji/js/hooks.min.map
AndroidJavaJishuBiji/js/reader.js
AndroidJavaJishuBiji/js/reader.js.map
AndroidJavaJishuBiji/js/reader.min.js
AndroidJavaJishuBiji/js/reader.min.map
AndroidJavaJishuBiji/js/hooks/__init__.py
AndroidJavaJishuBiji/js/hooks/extensions/__init__.py
AndroidJavaJishuBiji/js/hooks/extensions/highlight.js
AndroidJavaJishuBiji/js/libs/__init__.py
AndroidJavaJishuBiji/js/libs/jquery.min.js
AndroidJavaJishuBiji/js/libs/localforage.min.js
AndroidJavaJishuBiji/js/libs/screenfull.js
AndroidJavaJishuBiji/js/libs/screenfull.min.js
AndroidJavaJishuBiji/js/libs/zip.min.js
AndroidJavaJishuBiji/js/plugins/__init__.py
AndroidJavaJishuBiji/js/plugins/hypothesis.js
android_java_jishu_biji-2024.3.3.0.dist-info/METADATA
android_java_jishu_biji-2024.3.3.0.dist-info/WHEEL
android_java_jishu_biji-2024.3.3.0.dist-info/entry_points.txt
android_java_jishu_biji-2024.3.3.0.dist-info/top_level.txt
android_java_jishu_biji-2024.3.3.0.dist-info/RECORD
